LICENSE
MANIFEST.in
README.md
requirements.txt
setup.cfg
setup.py
geosrw/__init__.py
geosrw/geosrw.py
geosrw.egg-info/PKG-INFO
geosrw.egg-info/SOURCES.txt
geosrw.egg-info/dependency_links.txt
geosrw.egg-info/not-zip-safe
geosrw.egg-info/top_level.txt